{
	"configurations" : 
	[
		{
			"directories" : 
			[
				{
					"build" : ".",
					"jsonFile" : "directory-.-Debug-d0094a50bb2071803777.json",
					"minimumCMakeVersion" : 
					{
						"string" : "3.6.0"
					},
					"projectIndex" : 0,
					"source" : ".",
					"targetIndexes" : 
					[
						0
					]
				}
			],
			"name" : "Debug",
			"projects" : 
			[
				{
					"directoryIndexes" : 
					[
						0
					],
					"name" : "objectlearningtool",
					"targetIndexes" : 
					[
						0
					]
				}
			],
			"targets" : 
			[
				{
					"directoryIndex" : 0,
					"id" : "objectlearningtool::@6890427a1f51a3e7e1df",
					"jsonFile" : "target-objectlearningtool-Debug-b8d7248343917ea000c9.json",
					"name" : "objectlearningtool",
					"projectIndex" : 0
				}
			]
		}
	],
	"kind" : "codemodel",
	"paths" : 
	{
		"build" : "C:/Work/AndroidProjects/ObjectLearningTool/app/.cxx/Debug/3h2l5y6m/x86",
		"source" : "C:/Work/AndroidProjects/ObjectLearningTool/app/src/main/cpp"
	},
	"version" : 
	{
		"major" : 2,
		"minor" : 3
	}
}
